README.md
setup.cfg
setup.py
os_envload/__init__.py
os_envload/loader.py
os_envload.egg-info/PKG-INFO
os_envload.egg-info/SOURCES.txt
os_envload.egg-info/dependency_links.txt
os_envload.egg-info/top_level.txt